dxlclient/__init__.py
dxlclient/__main__.py
dxlclient/_callback_manager.py
dxlclient/_compat.py
dxlclient/_dxl_utils.py
dxlclient/_global_settings.py
dxlclient/_product_props.py
dxlclient/_request_manager.py
dxlclient/_thread_pool.py
dxlclient/_uuid_generator.py
dxlclient/broker.py
dxlclient/callbacks.py
dxlclient/client.py
dxlclient/client_config.py
dxlclient/exceptions.py
dxlclient/message.py
dxlclient/service.py
dxlclient/_cli/__init__.py
dxlclient/_cli/_cli_subcommands.py
dxlclient/_cli/_crypto.py
dxlclient/_cli/_management_service.py
oscrypto/__init__.py
oscrypto/_asn1.py
oscrypto/_asymmetric.py
oscrypto/_cipher_suites.py
oscrypto/_ecdsa.py
oscrypto/_errors.py
oscrypto/_ffi.py
oscrypto/_int.py
oscrypto/_pkcs1.py
oscrypto/_pkcs12.py
oscrypto/_pkcs5.py
oscrypto/_rand.py
oscrypto/_tls.py
oscrypto/_types.py
oscrypto/asymmetric.py
oscrypto/errors.py
oscrypto/kdf.py
oscrypto/keys.py
oscrypto/symmetric.py
oscrypto/tls.py
oscrypto/trust_list.py
oscrypto/util.py
oscrypto/version.py
oscrypto/_linux_bsd/__init__.py
oscrypto/_linux_bsd/trust_list.py
oscrypto/_mac/__init__.py
oscrypto/_mac/_common_crypto.py
oscrypto/_mac/_common_crypto_cffi.py
oscrypto/_mac/_common_crypto_ctypes.py
oscrypto/_mac/_core_foundation.py
oscrypto/_mac/_core_foundation_cffi.py
oscrypto/_mac/_core_foundation_ctypes.py
oscrypto/_mac/_security.py
oscrypto/_mac/_security_cffi.py
oscrypto/_mac/_security_ctypes.py
oscrypto/_mac/asymmetric.py
oscrypto/_mac/symmetric.py
oscrypto/_mac/tls.py
oscrypto/_mac/trust_list.py
oscrypto/_mac/util.py
oscrypto/_openssl/__init__.py
oscrypto/_openssl/_libcrypto.py
oscrypto/_openssl/_libcrypto_cffi.py
oscrypto/_openssl/_libcrypto_ctypes.py
oscrypto/_openssl/_libssl.py
oscrypto/_openssl/_libssl_cffi.py
oscrypto/_openssl/_libssl_ctypes.py
oscrypto/_openssl/asymmetric.py
oscrypto/_openssl/symmetric.py
oscrypto/_openssl/tls.py
oscrypto/_openssl/util.py
oscrypto/_win/__init__.py
oscrypto/_win/_advapi32.py
oscrypto/_win/_advapi32_cffi.py
oscrypto/_win/_advapi32_ctypes.py
dxlclient-5.7.0.1.dist-info/LICENSE
dxlclient-5.7.0.1.dist-info/METADATA
dxlclient-5.7.0.1.dist-info/WHEEL
dxlclient-5.7.0.1.dist-info/entry_points.txt
dxlclient-5.7.0.1.dist-info/top_level.txt
dxlclient-5.7.0.1.dist-info/RECORD
