Metadata-Version: 2.2
Name: dxlclient
Version: 5.7.0.1
Summary: McAfee Data Exchange Layer Client
Home-page: http://www.mcafee.com/
Author: McAfee, Inc.
License: Apache License 2.0
Keywords: opendxl,dxl,mcafee,client
Classifier: Topic :: Software Development :: Libraries :: Python Modules
Classifier: License :: OSI Approved :: Apache Software License
Classifier: Programming Language :: Python :: 3.7
Classifier: Programming Language :: Python :: 3.8
Classifier: Programming Language :: Python :: 3.9
Requires-Python: >=3.7
License-File: LICENSE
Requires-Dist: asn1crypto
Requires-Dist: configobj
Requires-Dist: msgpack<1.0.0,>=0.5
Requires-Dist: requests
Requires-Dist: PySocks
Provides-Extra: dev
Requires-Dist: futures; python_version == "3.7" and extra == "dev"
Requires-Dist: mock; extra == "dev"
Requires-Dist: nose; extra == "dev"
Requires-Dist: parameterized; extra == "dev"
Requires-Dist: astroid<2.3.0; python_version == "3.7" and extra == "dev"
Requires-Dist: astroid==2.3.3; python_version > "3.7" and extra == "dev"
Requires-Dist: pylint<=2.3.1; extra == "dev"
Requires-Dist: requests-mock; extra == "dev"
Requires-Dist: sphinx; extra == "dev"
Provides-Extra: test
Requires-Dist: futures; python_version == "3.7" and extra == "test"
Requires-Dist: mock; extra == "test"
Requires-Dist: nose; extra == "test"
Requires-Dist: parameterized; extra == "test"
Requires-Dist: astroid<2.3.0; python_version == "3.7" and extra == "test"
Requires-Dist: astroid==2.3.3; python_version > "3.7" and extra == "test"
Requires-Dist: pylint<=2.3.1; extra == "test"
Requires-Dist: requests-mock; extra == "test"
Dynamic: author
Dynamic: classifier
Dynamic: description
Dynamic: home-page
Dynamic: keywords
Dynamic: license
Dynamic: provides-extra
Dynamic: requires-dist
Dynamic: requires-python
Dynamic: summary
